{
  "articles": [
    {
      "title": "New Post",
      "body": "New Post",
      "author": "Buck",
      "id": 3
    },
    {
      "title": "Redirect Test",
      "body": "Redirect Test",
      "author": "Buck",
      "id": 4
    },
    {
      "title": "submittable?",
      "body": "llewpfenufhwiuyefpwenceufhapfeoiehwoepehvspedoif",
      "author": "buck",
      "id": 5
    },
    {
      "title": "Bootstrap Form Test",
      "body": "Figuring out Bootstrap stylings for the New Post form",
      "author": "Buck",
      "id": 6
    }
  ]
}